sdformat_mjcf/__init__.py
sdformat_mjcf/__version__.py
sdformat_mjcf/mjcf_to_sdformat/__init__.py
sdformat_mjcf/mjcf_to_sdformat/cli.py
sdformat_mjcf/mjcf_to_sdformat/mjcf_to_sdformat.py
sdformat_mjcf/mjcf_to_sdformat/converters/__init__.py
sdformat_mjcf/mjcf_to_sdformat/converters/geometry.py
sdformat_mjcf/mjcf_to_sdformat/converters/joint.py
sdformat_mjcf/mjcf_to_sdformat/converters/light.py
sdformat_mjcf/mjcf_to_sdformat/converters/link.py
sdformat_mjcf/mjcf_to_sdformat/converters/material.py
sdformat_mjcf/mjcf_to_sdformat/converters/sensor.py
sdformat_mjcf/mjcf_to_sdformat/converters/world.py
sdformat_mjcf/sdformat_to_mjcf/__init__.py
sdformat_mjcf/sdformat_to_mjcf/cli.py
sdformat_mjcf/sdformat_to_mjcf/sdf_kinematics.py
sdformat_mjcf/sdformat_to_mjcf/sdformat_to_mjcf.py
sdformat_mjcf/sdformat_to_mjcf/converters/__init__.py
sdformat_mjcf/sdformat_to_mjcf/converters/geometry.py
sdformat_mjcf/sdformat_to_mjcf/converters/joint.py
sdformat_mjcf/sdformat_to_mjcf/converters/light.py
sdformat_mjcf/sdformat_to_mjcf/converters/link.py
sdformat_mjcf/sdformat_to_mjcf/converters/material.py
sdformat_mjcf/sdformat_to_mjcf/converters/model.py
sdformat_mjcf/sdformat_to_mjcf/converters/root.py
sdformat_mjcf/sdformat_to_mjcf/converters/sensor.py
sdformat_mjcf/sdformat_to_mjcf/converters/world.py
sdformat_mjcf/utils/__init__.py
sdformat_mjcf/utils/defaults.py
sdformat_mjcf/utils/sdf_utils.py
sdformat_mjcf-0.1.2.dist-info/LICENSE
sdformat_mjcf-0.1.2.dist-info/METADATA
sdformat_mjcf-0.1.2.dist-info/WHEEL
sdformat_mjcf-0.1.2.dist-info/entry_points.txt
sdformat_mjcf-0.1.2.dist-info/top_level.txt
sdformat_mjcf-0.1.2.dist-info/RECORD
