Metadata-Version: 2.1
Name: sdformat-mjcf
Version: 0.1.2
Summary: Tool to convert between SDFormat and MJCF
Home-page: https://github.com/gazebosim/gz-mujoco
Author: Open Robotics
Author-email: info@openrobotics.org
License: Apache License 2.0
Classifier: License :: OSI Approved :: Apache Software License
Requires-Python: >=3.8
License-File: LICENSE
Requires-Dist: dm-control
